pandadoc_client/__init__.py
pandadoc_client/api_client.py
pandadoc_client/configuration.py
pandadoc_client/exceptions.py
pandadoc_client/model_utils.py
pandadoc_client/rest.py
pandadoc_client/api/__init__.py
pandadoc_client/api/api_logs_api.py
pandadoc_client/api/contacts_api.py
pandadoc_client/api/content_library_items_api.py
pandadoc_client/api/document_attachments_api.py
pandadoc_client/api/document_recipients_api.py
pandadoc_client/api/documents_api.py
pandadoc_client/api/folders_api_api.py
pandadoc_client/api/forms_api.py
pandadoc_client/api/members_api.py
pandadoc_client/api/o_auth_2_0_authentication_api.py
pandadoc_client/api/quotes_api.py
pandadoc_client/api/sections_api.py
pandadoc_client/api/templates_api.py
pandadoc_client/api/user_and_workspace_management_api.py
pandadoc_client/api/webhook_events_api.py
pandadoc_client/api/webhook_subscriptions_api.py
pandadoc_client/apis/__init__.py
pandadoc_client/model/__init__.py
pandadoc_client/model/add_member_request.py
pandadoc_client/model/add_member_response.py
pandadoc_client/model/api_log_details_response.py
pandadoc_client/model/api_log_list_response.py
pandadoc_client/model/api_log_list_response_results.py
pandadoc_client/model/contact_create_request.py
pandadoc_client/model/contact_details_response.py
pandadoc_client/model/contact_list_response.py
pandadoc_client/model/contact_update_request.py
pandadoc_client/model/content_library_item_list_response.py
pandadoc_client/model/content_library_item_list_response_results.py
pandadoc_client/model/content_library_item_response.py
pandadoc_client/model/content_library_item_response_created_by.py
pandadoc_client/model/create_user_request.py
pandadoc_client/model/create_user_request_user.py
pandadoc_client/model/create_user_request_workspaces.py
pandadoc_client/model/create_user_response.py
pandadoc_client/model/create_workspace_request.py
pandadoc_client/model/create_workspace_response.py
pandadoc_client/model/document_attachment_response.py
pandadoc_python_client-6.2.0.dist-info/LICENSE
pandadoc_python_client-6.2.0.dist-info/METADATA
pandadoc_python_client-6.2.0.dist-info/WHEEL
pandadoc_python_client-6.2.0.dist-info/top_level.txt
pandadoc_python_client-6.2.0.dist-info/RECORD
