Metadata-Version: 2.1
Name: pandadoc-python-client
Version: 6.2.0
Summary: PandaDoc Public API
Home-page: https://github.com/PandaDoc/pandadoc-api-python-client
Author: PandaDoc
Author-email: 
License: MIT
Keywords: OpenAPI,PandaDoc Public API
Requires-Python: >=3.6
License-File: LICENSE
Requires-Dist: urllib3 >=1.25.3
Requires-Dist: python-dateutil
